django_email_log/__init__.py
django_email_log/admin.py
django_email_log/apps.py
django_email_log/backends.py
django_email_log/checks.py
django_email_log/models.py
django_email_log/settings.py
django_email_log/urls.py
django_email_log/utils.py
django_email_log/views.py
django_email_log/locale/sk_SK/LC_MESSAGES/django.mo
django_email_log/locale/sk_SK/LC_MESSAGES/django.po
django_email_log/migrations/0001_initial.py
django_email_log/migrations/0002_auto_20210321_1145.py
django_email_log/migrations/__init__.py
django_email_log/static/django_email_log/css/admin.css
django_email_log/status_handlers/__init__.py
django_email_log/status_handlers/base.py
django_email_log/status_handlers/celery.py
django_email_log/templates/admin/django_email_log/email/change_form.html
django_email_log/templates/admin/django_email_log/email/change_list.html
django_email_log/templates/admin/django_email_log/email/part_tree.html
django_email_log_backend-0.3.6.dist-info/AUTHORS
django_email_log_backend-0.3.6.dist-info/LICENSE
django_email_log_backend-0.3.6.dist-info/METADATA
django_email_log_backend-0.3.6.dist-info/WHEEL
django_email_log_backend-0.3.6.dist-info/top_level.txt
django_email_log_backend-0.3.6.dist-info/RECORD
