Metadata-Version: 2.2
Name: django-email-log-backend
Version: 0.3.6
Summary: Django email log backend
Home-page: https://github.com/mireq/django-email-log-backend
Author: Miroslav Bendík
Author-email: miroslav.bendik@gmail.com
Classifier: Environment :: Web Environment
Classifier: Framework :: Django
Classifier: Intended Audience :: Developers
Classifier: Programming Language :: Python :: 3
Classifier: License :: OSI Approved :: MIT License
Classifier: Operating System :: OS Independent
Classifier: Topic :: Internet :: WWW/HTTP
Classifier: Topic :: Internet :: WWW/HTTP :: Dynamic Content
Requires-Python: >=3
License-File: LICENSE
License-File: AUTHORS
Dynamic: author
Dynamic: author-email
Dynamic: classifier
Dynamic: description
Dynamic: description-content-type
Dynamic: home-page
Dynamic: requires-python
Dynamic: summary
